llama_index/embeddings/jinaai/__init__.py
llama_index/embeddings/jinaai/base.py
llama_index_embeddings_jinaai-0.5.1.dist-info/METADATA
llama_index_embeddings_jinaai-0.5.1.dist-info/WHEEL
llama_index_embeddings_jinaai-0.5.1.dist-info/licenses/LICENSE
llama_index_embeddings_jinaai-0.5.1.dist-info/RECORD
